YAPCP-0.0.0.6.data/scripts/instotherpkg.sh
YAPCP-0.0.0.6.data/scripts/instsyspkg.sh
yapcp/__init__.py
yapcp/instotherpkg.sh
yapcp/instsyspkg.sh
yapcp/yapcp.py
YAPCP-0.0.0.6.dist-info/LICENSE
YAPCP-0.0.0.6.dist-info/METADATA
YAPCP-0.0.0.6.dist-info/WHEEL
YAPCP-0.0.0.6.dist-info/top_level.txt
YAPCP-0.0.0.6.dist-info/RECORD
